LICENSE
MANIFEST.in
README.md
setup.cfg
setup.py
autofactory/__init__.py
autofactory.egg-info/PKG-INFO
autofactory.egg-info/SOURCES.txt
autofactory.egg-info/dependency_links.txt
autofactory.egg-info/not-zip-safe
autofactory.egg-info/requires.txt
autofactory.egg-info/top_level.txt
autofactory/core/__init__.py
autofactory/core/registry.py
autofactory/django/__init__.py
autofactory/django/compat.py
autofactory/django/factories.py
autofactory/django/introspector.py
autofactory/django/maker.py
autofactory/django/options.py
autofactory/django/shortcuts.py
autofactory/django/builders/__init__.py
autofactory/django/builders/booleans.py
autofactory/django/builders/concrete.py
autofactory/django/builders/datetimes.py
autofactory/django/builders/misc.py
autofactory/django/builders/numbers.py
autofactory/django/builders/relationships.py
autofactory/django/builders/strings.py